yalambda/__init__.py
yalambda/__main__.py
yalambda/async_utils.py
yalambda/core.py
yalambda/py.typed
yalambda/when.py
yalambda-0.6.0.dist-info/LICENSE
yalambda-0.6.0.dist-info/WHEEL
yalambda-0.6.0.dist-info/METADATA
yalambda-0.6.0.dist-info/RECORD
