Metadata-Version: 2.1
Name: yalambda
Version: 0.6.0
Summary: Yandex.Cloud Functions toolkit
Home-page: https://github.com/decorator-factory/yalambda
License: MIT
Author: decorator-factory
Author-email: 42166884+decorator-factory@users.noreply.github.com
Requires-Python: >=3.8
Classifier: Development Status :: 2 - Pre-Alpha
Classifier: License :: OSI Approved :: MIT License
Classifier: Programming Language :: Python :: 3
Classifier: Programming Language :: Python :: 3.8
Classifier: Programming Language :: Python :: 3.9
Requires-Dist: dataclass-factory (>=2.11,<3.0)
Requires-Dist: multidict (>=5.2.0,<6.0.0)
